LICENSE.txt
MANIFEST.in
README.rst
requirements.txt
setup.py
templateParse.egg-info/PKG-INFO
templateParse.egg-info/SOURCES.txt
templateParse.egg-info/dependency_links.txt
templateParse.egg-info/entry_points.txt
templateParse.egg-info/not-zip-safe
templateParse.egg-info/requires.txt
templateParse.egg-info/top_level.txt
templateparse/__init__.py
templateparse/main.py
templateparse/extract/__init__.py
templateparse/extract/invoice_template.py
templateparse/extract/loader.py
templateparse/extract/plugins/__init__.py
templateparse/extract/plugins/__interface__.py
templateparse/extract/plugins/lines.py
templateparse/extract/templates/ch/ch.pcengines.yml
templateparse/extract/templates/com/com.amazon.aws.yml
templateparse/extract/templates/com/com.apps4rent.yml
templateparse/extract/templates/com/com.binarylife.yml
templateparse/extract/templates/com/com.bloomberg.yml
templateparse/extract/templates/com/com.cloudns.yml
templateparse/extract/templates/com/com.datadoghq.yml
templateparse/extract/templates/com/com.digitalocean.yml
templateparse/extract/templates/com/com.envato.yml
templateparse/extract/templates/com/com.expressvpn.yml
templateparse/extract/templates/com/com.flipkart.WSRetail.yml
templateparse/extract/templates/com/com.ftserussell.yml
templateparse/extract/templates/com/com.github.yml
templateparse/extract/templates/com/com.globalsign.yml
templateparse/extract/templates/com/com.google.adwords.hk.yml
templateparse/extract/templates/com/com.hobohost.yml
templateparse/extract/templates/com/com.linode.yml
templateparse/extract/templates/com/com.microsoftonline.hk-v2017.yml
templateparse/extract/templates/com/com.microsoftonline.hk.yml
templateparse/extract/templates/com/com.namecheap.yml
templateparse/extract/templates/com/com.namesilo.yml
templateparse/extract/templates/com/com.nodisto.yml
templateparse/extract/templates/com/com.nyxdata.yml
templateparse/extract/templates/com/com.oyo.invoice.yml
templateparse/extract/templates/com/com.packtpub.yml
templateparse/extract/templates/com/com.pixartprinting.yml
templateparse/extract/templates/com/com.scaleway.yml
templateparse/extract/templates/com/com.textmaster.yml
templateparse/extract/templates/com/com.tmx.yml
templateparse/extract/templates/com/com.twitter.de.yml
