Metadata-Version: 1.0
Name: templateParse
Version: 0.1.200
Summary: Python parser to extract data from pdf invoice
Home-page: https://github.com/konigle/templateparser
Author: Ashish Kumar
Author-email: hi.ashish.kr@gmail.com
License: MIT
Platform: UNKNOWN
